README.rst
setup.py
alder/__init__.py
alder/__metadata__.py
alder/db.py
alder.egg-info/PKG-INFO
alder.egg-info/SOURCES.txt
alder.egg-info/dependency_links.txt
alder.egg-info/requires.txt
alder.egg-info/top_level.txt
alder/aid/__init__.py
alder/aid/rand.py
alder/aid/traverse.py
alder/index/__init__.py
alder/index/hdht.py
alder/store/__init__.py
alder/store/files.py
alder/store/serial.py