Metadata-Version: 1.1
Name: alder
Version: 0.1.0
Summary: Asynchrounous Lexical Distributed Event Roster
Home-page: https://github.com/AlderDHT/alder.git
Author: Samuel M. Smith
Author-email: smith.samuel.m@gmail.com
License: Apache2
Download-URL: https://github.com/AlderDHT/alder/archive/master.zip
Keywords: Asynchrounous Lexical Distributed Event Roster Consensus DHT Key Value Store
Platform: UNKNOWN
